nail/__init__.py
nail/main.py
nail/core/__init__.py
nail/core/chat.py
nail/core/file_editor.py
nail/core/loading_decorator.py
nail/core/config/__init__.py
nail/core/config/local_config_utils.py
nail/core/config/user_config_utils.py
nail/core/language_models/__init__.py
nail/core/language_models/language_model.py
nail/core/language_models/open_ai.py
nail/core/language_models/supported_models.py
nail/core/prompt/__init__.py
nail/core/prompt/context_compiler.py
nail/core/prompt/formatting_utils.py
nail/core/prompt/prompt.py
nail/tools/__init__.py
nail/tools/build_file.py
nail/tools/build_readme.py
nail/tools/build_spec_file.py
nail/tools/debug_file.py
nail/tools/explain_file.py
nail/tools/modify_file.py
tests/__init__.py
tests/test_main.py
tests/core/__init__.py
tests/core/test_chat.py
tests/core/test_config_utils.py
tests/core/test_file_editor.py
nail-0.1.2.dist-info/LICENSE
nail-0.1.2.dist-info/METADATA
nail-0.1.2.dist-info/WHEEL
nail-0.1.2.dist-info/entry_points.txt
nail-0.1.2.dist-info/top_level.txt
nail-0.1.2.dist-info/RECORD
