Metadata-Version: 2.1
Name: nail
Version: 0.1.2
Summary: A CLI tool for speeding up development using LLMs
Home-page: https://github.com/edsaav/nail
Author: Edward Saavedra
Author-email: edsaav@gmail.com
Classifier: Programming Language :: Python :: 3
Classifier: License :: OSI Approved :: MIT License
Classifier: Operating System :: OS Independent
License-File: LICENSE
Requires-Dist: click
Requires-Dist: openai
Requires-Dist: termcolor
Requires-Dist: PyYAML
Requires-Dist: rich
